api_throttler/__init__.py
api_throttler/fixed_window_throttler.py
api_throttler/fixed_window_throttler_redis.py
api_throttler/sliding_window_throttler.py
api_throttler/sliding_window_throttler_redis.py
api_throttler/throttler.py
api_throttler-0.3.1.dist-info/LICENSE
api_throttler-0.3.1.dist-info/METADATA
api_throttler-0.3.1.dist-info/WHEEL
api_throttler-0.3.1.dist-info/top_level.txt
api_throttler-0.3.1.dist-info/RECORD
