Metadata-Version: 2.1
Name: api-throttler
Version: 0.3.1
Summary: A python toolkit to enforce API rate limit on the backend
Home-page: https://github.com/berknology/api-throttler
Author: He Hao
Author-email: berknology@gmail.com
License: BSD license
Keywords: ratelimit,rate-limit,rate-limiter,throttling,throttle,throttler,api,decorator
Platform: UNKNOWN
Classifier: Development Status :: 2 - Pre-Alpha
Classifier: Intended Audience :: Developers
Classifier: License :: OSI Approved :: BSD License
Classifier: Natural Language :: English
Classifier: Programming Language :: Python :: 3.7
Classifier: Programming Language :: Python :: 3.8
Requires-Dist: redis
